{
  "language_code": "ro",
  "title": "COMPETIȚIA DE SĂRITURI 2",
  "robin": "Robin",
  "starfire": "Starfire",
  "raven": "Raven",
  "cyborg": "Cyborg",
  "beastboy": "Beastboy",
  "gizmo": "Gizmo",
  "jinx": "Jinx",
  "mammoth": "Mammoth",
  "painbot": "Pain-Bot",
  "terra": "Terra",
  "bumblebee": "Bumblebee ",
  "aqualad": "Aqualad",
  "kidflash": "Kid Flash",
  "batman": "Batman",
  "superman": "Superman",
  "harleyquinn": "Harley Quinn",
  "slade": "Slade",
  "mothermaeeye": "Mama mae-eye",
  "trigon": "Trigon",
  "brotherblood": "Brother Blood",
  "credits_produced": "Produs de",
  "credits_developed": "Dezvoltat de",
  "select_color": "CULOARE",
  "select_endless": "FĂRĂ SFÂRŞIT",
  "select_ready": "GATA!",
  "select_color_mobile": "APASĂ PENTRU A SCHIMBA CULOAREA",
  "controls_attack": "ATAC",
  "controls_move": "DEPLASEAZĂ-TE",
  "controls_ok": "OK",
  "controls_back": "ÎNAPOI",
  "controls_jump": "SARI",
  "controls_special": "SPECIAL",
  "controls_tap": "ATINGE",
  "controls_tap_here": "APASĂ AICI",
  "battle_ready": "GATA",
  "battle_wins": "VICTORIE!",
  "battle_pause": "PAUZĂ",
  "battle_tiebreaker": "E RÂNDUL TĂU!",
  "battle_quit_confirm": "RENUNȚI LA BĂTĂLIE?",
  "unlock_character": "PERSONAJ NOU DEBLOCAT",
  "unlock_color": "CULOARE NOUĂ DEBLOCATĂ",
  "unlock_gamemode": "MOD DE JOC NOU DEBLOCAT",
  "endless_battle": "LUPTĂ",
  "endless_best_character": "SCOR MAXIM PERSONAJ",
  "endless_best_overall": "SCOR MAXIM GENERAL",
  "mode_endless": "MOD NELIMITAT",
  "mode_rivals": "MOD RIVALI"
}